mixemup.py
mixemup-2.1.0.dist-info/entry_points.txt
mixemup-2.1.0.dist-info/WHEEL
mixemup-2.1.0.dist-info/METADATA
mixemup-2.1.0.dist-info/RECORD
